statnett_api_client/__init__.py
statnett_api_client/client.py
statnett_api_client/config.py
statnett_api_client/constants.py
statnett_api_client/topics.py
statnett_api_client-0.1.5.dist-info/LICENSE
statnett_api_client-0.1.5.dist-info/METADATA
statnett_api_client-0.1.5.dist-info/WHEEL
statnett_api_client-0.1.5.dist-info/top_level.txt
statnett_api_client-0.1.5.dist-info/RECORD
