Metadata-Version: 2.1
Name: statnett-api-client
Version: 0.1.5
Summary: Statnett API Client
Home-page: https://github.com/viktorsapozhok/statnett-api-client
Author: Alex Piskun
Author-email: piskun.aleksey@gmail.com
License: UNKNOWN
Keywords: Statnett,API,Nordic power flow,Nordic power balance
Platform: UNKNOWN
Classifier: Programming Language :: Python :: 3
Classifier: License :: OSI Approved :: MIT License
Classifier: Operating System :: OS Independent
Requires-Python: >=3.6
Requires-Dist: requests
Requires-Dist: pandas (>=0.24.0)
